whitson_tool_helper/__init__.py
whitson_tool_helper/logger.py
whitson_tool_helper/timeout.py
whitson_tool_helper/whitson_exceptions.py
whitson_tool_helper/messaging/helper.py
whitson_tool_helper/messaging/main.py
whitson_tool_helper/messaging/pubsub.py
whitson_tool_helper/messaging/rabbitmq.py
whitson_tool_helper-1.0.1.dist-info/METADATA
whitson_tool_helper-1.0.1.dist-info/WHEEL
whitson_tool_helper-1.0.1.dist-info/top_level.txt
whitson_tool_helper-1.0.1.dist-info/RECORD
