Metadata-Version: 2.4
Name: whitson_tool_helper
Version: 1.0.1
Summary: A Toolbox for whitson cloud software solutions
Author-email: Markus Blytt <blytt@whitson.com>, Jason Hu <jason@whitson.com>, Arnaud Hoffmann <arnaud@whitson.com>
Classifier: Programming Language :: Python :: 3
Classifier: License :: OSI Approved :: MIT License
Classifier: Operating System :: OS Independent
Requires-Python: >=3.11
Requires-Dist: pika==1.3.1
Requires-Dist: google-auth==2.40.3
Requires-Dist: google-cloud-pubsub==2.14.0
Requires-Dist: google-cloud-storage==3.1.1
Requires-Dist: google-cloud-logging==3.5.0
